gridding/__init__.py
gridding/__main__.py
gridding/coordinates.py
gridding/gis.py
gridding/grid.py
gridding/projection.py
gridding/repository.py
gridding/utils/__init__.py
gridding/utils/fr_dictionary.txt
gridding/utils/hash.py
gridding/utils/normalize.py
gridding_py-1.0.0.dist-info/LICENSE
gridding_py-1.0.0.dist-info/METADATA
gridding_py-1.0.0.dist-info/WHEEL
gridding_py-1.0.0.dist-info/entry_points.txt
gridding_py-1.0.0.dist-info/top_level.txt
gridding_py-1.0.0.dist-info/RECORD
