Metadata-Version: 2.2
Name: gridding-py
Version: 1.0.0
Summary: Build geographical grids
Author-email: Cyril Dever <cdever@pep-s.com>
License: MIT License
Project-URL: Homepage, https://github.com/cyrildever/gridding
Keywords: geographical,grid,carreau,carroyage,geodesic,tile,wgs84,utm
Classifier: Programming Language :: Python :: 3
Classifier: License :: OSI Approved :: MIT License
Classifier: Operating System :: OS Independent
Requires-Python: >=3.10.2
License-File: LICENSE
